cafex_api/__init__.py
cafex_api/api_exceptions.py
cafex_api/graphql_utils.py
cafex_api/request_builder.py
cafex_api/socket_handler.py
cafex_api-1.0.0.dist-info/METADATA
cafex_api-1.0.0.dist-info/WHEEL
cafex_api-1.0.0.dist-info/top_level.txt
cafex_api-1.0.0.dist-info/RECORD
