Metadata-Version: 2.4
Name: cafex-api
Version: 1.0.0
Summary: API Library
Author-email: QA Automation Team <qa_automation@gmail.com>
Project-URL: Homepage, https://example.com
Project-URL: Documentation, https://readthedocs.org
Project-URL: Repository, https://github.com/me/spam.git
Project-URL: Issues, https://github.com/me/spam/issues
Project-URL: Changelog, https://github.com/me/spam/blob/master/CHANGELOG.md
Keywords: api,api testing,pytest,automation
Classifier: Programming Language :: Python :: 3
Classifier: Operating System :: OS Independent
Requires-Python: >=3.12
Requires-Dist: cafex-core>=1.0.0
Requires-Dist: zeep==4.2.1
Requires-Dist: websocket-client==1.8.0
Requires-Dist: gql==3.5.2
